kmedoids/kmedoids.cpython-311-x86_64-linux-gnu.so
kmedoids/__init__.py
kmedoids_debug-0.4.1.dist-info/METADATA
kmedoids_debug-0.4.1.dist-info/RECORD
kmedoids_debug-0.4.1.dist-info/WHEEL
kmedoids_debug-0.4.1.dist-info/license_files/LICENSE
